nanoinject
