Metadata-Version: 2.1
Name: nanoinject
Version: 1.0.1
Summary: Nanoinject is a terrifically small and simple dependency injection container
Home-page: https://github.com/berry-langerak/nanoinject
Author: Berry Langerak
Author-email: berry.langerak@gmail.com
License: UNKNOWN
Platform: UNKNOWN
Classifier: Programming Language :: Python :: 3
Classifier: License :: OSI Approved :: MIT License
Classifier: Operating System :: OS Independent
Classifier: Development Status :: 5 - Production/Stable
Classifier: Intended Audience :: Developers
Requires-Python: >=3.6
Provides-Extra: test
